{"paging":{"pageIndex":1,"pageSize":500,"total":25},"baseComponent":{"id":"AYJQm0b0JWCK4jrcu79-","key":"fga-eps-mds_2022.1-EuPescador-User","name":"2022.1-EuPescador-User","qualifier":"TRK","measures":[{"metric":"duplicated_lines_density","value":"0.0","bestValue":true},{"metric":"functions","value":"22"},{"metric":"test_execution_time","value":"11"},{"metric":"security_rating","value":"1.0","bestValue":true},{"metric":"tests","value":"10"},{"metric":"files","value":"15"},{"metric":"complexity","value":"53"},{"metric":"ncloc","value":"413"},{"metric":"coverage","value":"58.6","bestValue":false},{"metric":"reliability_rating","value":"1.0","bestValue":true},{"metric":"comment_lines_density","value":"1.0","bestValue":false},{"metric":"test_success_density","value":"100.0","bestValue":true}]},"components":[{"id":"AYJVb5ukILU70yBXuTi6","key":"fga-eps-mds_2022.1-EuPescador-User:src/controllers/adminController.ts","name":"adminController.ts","qualifier":"FIL","path":"src/controllers/adminController.ts","language":"ts","measures":[{"metric":"complexity","value":"16"},{"metric":"functions","value":"2"},{"metric":"ncloc","value":"77"},{"metric":"coverage","value":"0.0","bestValue":false},{"metric":"reliability_rating","value":"1.0","bestValue":true},{"metric":"security_rating","value":"1.0","bestValue":true},{"metric":"comment_lines_density","value":"3.8","bestValue":false},{"metric":"files","value":"1"},{"metric":"duplicated_lines_density","value":"0.0","bestValue":true},{"metric":"test_success_density","value":"100.0","bestValue":true}]},{"id":"AYJVb5ukILU70yBXuTi0","key":"fga-eps-mds_2022.1-EuPescador-User:src/routes/adminRoutes.ts","name":"adminRoutes.ts","qualifier":"FIL","path":"src/routes/adminRoutes.ts","language":"ts","measures":[{"metric":"complexity","value":"2"},{"metric":"functions","value":"2"},{"metric":"ncloc","value":"11"},{"metric":"coverage","value":"0.0","bestValue":false},{"metric":"reliability_rating","value":"1.0","bestValue":true},{"metric":"security_rating","value":"1.0","bestValue":true},{"metric":"comment_lines_density","value":"0.0","bestValue":false},{"metric":"files","value":"1"},{"metric":"duplicated_lines_density","value":"0.0","bestValue":true},{"metric":"test_success_density","value":"100.0","bestValue":true}]},{"id":"AYJVb5ukILU70yBXuTi4","key":"fga-eps-mds_2022.1-EuPescador-User:src/app.ts","name":"app.ts","qualifier":"FIL","path":"src/app.ts","language":"ts","measures":[{"metric":"complexity","value":"0"},{"metric":"functions","value":"0"},{"metric":"ncloc","value":"11"},{"metric":"coverage","value":"0.0","bestValue":false},{"metric":"reliability_rating","value":"1.0","bestValue":true},{"metric":"security_rating","value":"1.0","bestValue":true},{"metric":"comment_lines_density","value":"0.0","bestValue":false},{"metric":"files","value":"1"},{"metric":"duplicated_lines_density","value":"0.0","bestValue":true},{"metric":"test_success_density","value":"100.0","bestValue":true}]},{"id":"AYJVb5ukILU70yBXuTi_","key":"fga-eps-mds_2022.1-EuPescador-User:src/middleware/authUser.ts","name":"authUser.ts","qualifier":"FIL","path":"src/middleware/authUser.ts","language":"ts","measures":[{"metric":"complexity","value":"1"},{"metric":"functions","value":"1"},{"metric":"ncloc","value":"6"},{"metric":"coverage","value":"71.4","bestValue":false},{"metric":"reliability_rating","value":"1.0","bestValue":true},{"metric":"security_rating","value":"1.0","bestValue":true},{"metric":"comment_lines_density","value":"0.0","bestValue":false},{"metric":"files","value":"1"},{"metric":"duplicated_lines_density","value":"0.0","bestValue":true},{"metric":"test_success_density","value":"100.0","bestValue":true}]},{"id":"AYJVb5ukILU70yBXuTix","key":"fga-eps-mds_2022.1-EuPescador-User:src/config","name":"config","qualifier":"DIR","path":"src/config","measures":[{"metric":"duplicated_lines_density","value":"0.0","bestValue":true},{"metric":"functions","value":"0"},{"metric":"security_rating","value":"1.0","bestValue":true},{"metric":"files","value":"1"},{"metric":"complexity","value":"3"},{"metric":"ncloc","value":"21"},{"metric":"coverage","value":"79.2","bestValue":false},{"metric":"reliability_rating","value":"1.0","bestValue":true},{"metric":"comment_lines_density","value":"0.0","bestValue":false}]},{"id":"AYJVb5ukILU70yBXuTi8","key":"fga-eps-mds_2022.1-EuPescador-User:src/controllers","name":"controllers","qualifier":"DIR","path":"src/controllers","measures":[{"metric":"duplicated_lines_density","value":"0.0","bestValue":true},{"metric":"functions","value":"8"},{"metric":"security_rating","value":"1.0","bestValue":true},{"metric":"files","value":"3"},{"metric":"complexity","value":"34"},{"metric":"ncloc","value":"244"},{"metric":"coverage","value":"60.0","bestValue":false},{"metric":"reliability_rating","value":"1.0","bestValue":true},{"metric":"comment_lines_density","value":"1.2","bestValue":false}]},{"id":"AYJVb5ukILU70yBXuTiw","key":"fga-eps-mds_2022.1-EuPescador-User:src/config/database.ts","name":"database.ts","qualifier":"FIL","path":"src/config/database.ts","language":"ts","measures":[{"metric":"complexity","value":"3"},{"metric":"functions","value":"0"},{"metric":"ncloc","value":"21"},{"metric":"coverage","value":"79.2","bestValue":false},{"metric":"reliability_rating","value":"1.0","bestValue":true},{"metric":"security_rating","value":"1.0","bestValue":true},{"metric":"comment_lines_density","value":"0.0","bestValue":false},{"metric":"files","value":"1"},{"metric":"duplicated_lines_density","value":"0.0","bestValue":true},{"metric":"test_success_density","value":"100.0","bestValue":true}]},{"id":"AYJVb5ukILU70yBXuTi9","key":"fga-eps-mds_2022.1-EuPescador-User:src/utils/generateToken.ts","name":"generateToken.ts","qualifier":"FIL","path":"src/utils/generateToken.ts","language":"ts","measures":[{"metric":"complexity","value":"2"},{"metric":"functions","value":"1"},{"metric":"ncloc","value":"9"},{"metric":"coverage","value":"0.0","bestValue":false},{"metric":"reliability_rating","value":"1.0","bestValue":true},{"metric":"security_rating","value":"1.0","bestValue":true},{"metric":"comment_lines_density","value":"0.0","bestValue":false},{"metric":"files","value":"1"},{"metric":"duplicated_lines_density","value":"0.0","bestValue":true},{"metric":"test_success_density","value":"100.0","bestValue":true}]},{"id":"AYJVb5ukILU70yBXuTjA","key":"fga-eps-mds_2022.1-EuPescador-User:src/middleware","name":"middleware","qualifier":"DIR","path":"src/middleware","measures":[{"metric":"duplicated_lines_density","value":"0.0","bestValue":true},{"metric":"functions","value":"1"},{"metric":"security_rating","value":"1.0","bestValue":true},{"metric":"files","value":"1"},{"metric":"complexity","value":"1"},{"metric":"ncloc","value":"6"},{"metric":"coverage","value":"71.4","bestValue":false},{"metric":"reliability_rating","value":"1.0","bestValue":true},{"metric":"comment_lines_density","value":"0.0","bestValue":false}]},{"id":"AYJVb5ukILU70yBXuTjD","key":"fga-eps-mds_2022.1-EuPescador-User:src/models","name":"models","qualifier":"DIR","path":"src/models","measures":[{"metric":"duplicated_lines_density","value":"0.0","bestValue":true},{"metric":"functions","value":"0"},{"metric":"security_rating","value":"1.0","bestValue":true},{"metric":"files","value":"2"},{"metric":"complexity","value":"0"},{"metric":"ncloc","value":"32"},{"metric":"coverage","value":"100.0","bestValue":true},{"metric":"reliability_rating","value":"1.0","bestValue":true},{"metric":"comment_lines_density","value":"0.0","bestValue":false}]},{"id":"AYJVb5ukILU70yBXuTi1","key":"fga-eps-mds_2022.1-EuPescador-User:src/routes/router.ts","name":"router.ts","qualifier":"FIL","path":"src/routes/router.ts","language":"ts","measures":[{"metric":"complexity","value":"0"},{"metric":"functions","value":"0"},{"metric":"ncloc","value":"9"},{"metric":"coverage","value":"0.0","bestValue":false},{"metric":"reliability_rating","value":"1.0","bestValue":true},{"metric":"security_rating","value":"1.0","bestValue":true},{"metric":"comment_lines_density","value":"10.0","bestValue":false},{"metric":"files","value":"1"},{"metric":"duplicated_lines_density","value":"0.0","bestValue":true},{"metric":"test_success_density","value":"100.0","bestValue":true}]},{"id":"AYJVb5ukILU70yBXuTi3","key":"fga-eps-mds_2022.1-EuPescador-User:src/routes","name":"routes","qualifier":"DIR","path":"src/routes","measures":[{"metric":"duplicated_lines_density","value":"0.0","bestValue":true},{"metric":"functions","value":"8"},{"metric":"security_rating","value":"1.0","bestValue":true},{"metric":"files","value":"4"},{"metric":"complexity","value":"8"},{"metric":"ncloc","value":"48"},{"metric":"coverage","value":"0.0","bestValue":false},{"metric":"reliability_rating","value":"1.0","bestValue":true},{"metric":"comment_lines_density","value":"2.0","bestValue":false}]},{"id":"AYJVb5ukILU70yBXuTi7","key":"fga-eps-mds_2022.1-EuPescador-User:src/controllers/sendMailController.ts","name":"sendMailController.ts","qualifier":"FIL","path":"src/controllers/sendMailController.ts","language":"ts","measures":[{"metric":"complexity","value":"3"},{"metric":"functions","value":"2"},{"metric":"ncloc","value":"46"},{"metric":"coverage","value":"0.0","bestValue":false},{"metric":"reliability_rating","value":"1.0","bestValue":true},{"metric":"security_rating","value":"1.0","bestValue":true},{"metric":"comment_lines_density","value":"0.0","bestValue":false},{"metric":"files","value":"1"},{"metric":"duplicated_lines_density","value":"0.0","bestValue":true},{"metric":"test_success_density","value":"100.0","bestValue":true}]},{"id":"AYJVb5ukILU70yBXuTi2","key":"fga-eps-mds_2022.1-EuPescador-User:src/routes/sendMailRoutes.ts","name":"sendMailRoutes.ts","qualifier":"FIL","path":"src/routes/sendMailRoutes.ts","language":"ts","measures":[{"metric":"complexity","value":"2"},{"metric":"functions","value":"2"},{"metric":"ncloc","value":"11"},{"metric":"coverage","value":"0.0","bestValue":false},{"metric":"reliability_rating","value":"1.0","bestValue":true},{"metric":"security_rating","value":"1.0","bestValue":true},{"metric":"comment_lines_density","value":"0.0","bestValue":false},{"metric":"files","value":"1"},{"metric":"duplicated_lines_density","value":"0.0","bestValue":true},{"metric":"test_success_density","value":"100.0","bestValue":true}]},{"id":"AYJVb5ukILU70yBXuTjE","key":"fga-eps-mds_2022.1-EuPescador-User:src/services/sendMailService.ts","name":"sendMailService.ts","qualifier":"FIL","path":"src/services/sendMailService.ts","language":"ts","measures":[{"metric":"complexity","value":"1"},{"metric":"functions","value":"1"},{"metric":"ncloc","value":"29"},{"metric":"coverage","value":"0.0","bestValue":false},{"metric":"reliability_rating","value":"1.0","bestValue":true},{"metric":"security_rating","value":"1.0","bestValue":true},{"metric":"comment_lines_density","value":"0.0","bestValue":false},{"metric":"files","value":"1"},{"metric":"duplicated_lines_density","value":"0.0","bestValue":true},{"metric":"test_success_density","value":"100.0","bestValue":true}]},{"id":"AYJVb5ukILU70yBXuTiy","key":"fga-eps-mds_2022.1-EuPescador-User:src/server.ts","name":"server.ts","qualifier":"FIL","path":"src/server.ts","language":"ts","measures":[{"metric":"complexity","value":"4"},{"metric":"functions","value":"3"},{"metric":"ncloc","value":"13"},{"metric":"coverage","value":"0.0","bestValue":false},{"metric":"reliability_rating","value":"1.0","bestValue":true},{"metric":"security_rating","value":"1.0","bestValue":true},{"metric":"comment_lines_density","value":"0.0","bestValue":false},{"metric":"files","value":"1"},{"metric":"duplicated_lines_density","value":"0.0","bestValue":true},{"metric":"test_success_density","value":"100.0","bestValue":true}]},{"id":"AYJVb5ukILU70yBXuTjF","key":"fga-eps-mds_2022.1-EuPescador-User:src/services","name":"services","qualifier":"DIR","path":"src/services","measures":[{"metric":"duplicated_lines_density","value":"0.0","bestValue":true},{"metric":"functions","value":"1"},{"metric":"security_rating","value":"1.0","bestValue":true},{"metric":"files","value":"1"},{"metric":"complexity","value":"1"},{"metric":"ncloc","value":"29"},{"metric":"coverage","value":"0.0","bestValue":false},{"metric":"reliability_rating","value":"1.0","bestValue":true},{"metric":"comment_lines_density","value":"0.0","bestValue":false}]},{"id":"AYJVb5ukILU70yBXuTjG","key":"fga-eps-mds_2022.1-EuPescador-User:src","name":"src","qualifier":"DIR","path":"src","measures":[{"metric":"duplicated_lines_density","value":"0.0","bestValue":true},{"metric":"functions","value":"22"},{"metric":"security_rating","value":"1.0","bestValue":true},{"metric":"files","value":"15"},{"metric":"complexity","value":"53"},{"metric":"ncloc","value":"413"},{"metric":"coverage","value":"58.6","bestValue":false},{"metric":"reliability_rating","value":"1.0","bestValue":true},{"metric":"comment_lines_density","value":"1.0","bestValue":false}]},{"id":"AYJVb5ukILU70yBXuTjI","key":"fga-eps-mds_2022.1-EuPescador-User:test/controllers","name":"test/controllers","qualifier":"DIR","path":"test/controllers","measures":[{"metric":"test_execution_time","value":"11"},{"metric":"security_rating","value":"1.0","bestValue":true},{"metric":"tests","value":"10"},{"metric":"reliability_rating","value":"1.0","bestValue":true},{"metric":"test_success_density","value":"100.0","bestValue":true}]},{"id":"AYJVb5ukILU70yBXuTjC","key":"fga-eps-mds_2022.1-EuPescador-User:src/models/token.ts","name":"token.ts","qualifier":"FIL","path":"src/models/token.ts","language":"ts","measures":[{"metric":"complexity","value":"0"},{"metric":"functions","value":"0"},{"metric":"ncloc","value":"10"},{"metric":"coverage","value":"100.0","bestValue":true},{"metric":"reliability_rating","value":"1.0","bestValue":true},{"metric":"security_rating","value":"1.0","bestValue":true},{"metric":"comment_lines_density","value":"0.0","bestValue":false},{"metric":"files","value":"1"},{"metric":"duplicated_lines_density","value":"0.0","bestValue":true},{"metric":"test_success_density","value":"100.0","bestValue":true}]},{"id":"AYJVb5ukILU70yBXuTjB","key":"fga-eps-mds_2022.1-EuPescador-User:src/models/user.ts","name":"user.ts","qualifier":"FIL","path":"src/models/user.ts","language":"ts","measures":[{"metric":"complexity","value":"0"},{"metric":"functions","value":"0"},{"metric":"ncloc","value":"22"},{"metric":"coverage","value":"100.0","bestValue":true},{"metric":"reliability_rating","value":"1.0","bestValue":true},{"metric":"security_rating","value":"1.0","bestValue":true},{"metric":"comment_lines_density","value":"0.0","bestValue":false},{"metric":"files","value":"1"},{"metric":"duplicated_lines_density","value":"0.0","bestValue":true},{"metric":"test_success_density","value":"100.0","bestValue":true}]},{"id":"AYJVb5ukILU70yBXuTjH","key":"fga-eps-mds_2022.1-EuPescador-User:test/controllers/userController.spec.ts","name":"userController.spec.ts","qualifier":"UTS","path":"test/controllers/userController.spec.ts","language":"ts","measures":[{"metric":"reliability_rating","value":"1.0","bestValue":true},{"metric":"security_rating","value":"1.0","bestValue":true},{"metric":"test_execution_time","value":"11"},{"metric":"tests","value":"10"},{"metric":"duplicated_lines_density","value":"0.0","bestValue":true},{"metric":"test_success_density","value":"100.0","bestValue":true}]},{"id":"AYJVb5ukILU70yBXuTi5","key":"fga-eps-mds_2022.1-EuPescador-User:src/controllers/userController.ts","name":"userController.ts","qualifier":"FIL","path":"src/controllers/userController.ts","language":"ts","measures":[{"metric":"complexity","value":"15"},{"metric":"functions","value":"4"},{"metric":"ncloc","value":"121"},{"metric":"coverage","value":"82.9","bestValue":false},{"metric":"reliability_rating","value":"1.0","bestValue":true},{"metric":"security_rating","value":"1.0","bestValue":true},{"metric":"comment_lines_density","value":"0.0","bestValue":false},{"metric":"files","value":"1"},{"metric":"duplicated_lines_density","value":"0.0","bestValue":true},{"metric":"test_success_density","value":"100.0","bestValue":true}]},{"id":"AYJVb5ukILU70yBXuTiz","key":"fga-eps-mds_2022.1-EuPescador-User:src/routes/userRoutes.ts","name":"userRoutes.ts","qualifier":"FIL","path":"src/routes/userRoutes.ts","language":"ts","measures":[{"metric":"complexity","value":"4"},{"metric":"functions","value":"4"},{"metric":"ncloc","value":"17"},{"metric":"coverage","value":"0.0","bestValue":false},{"metric":"reliability_rating","value":"1.0","bestValue":true},{"metric":"security_rating","value":"1.0","bestValue":true},{"metric":"comment_lines_density","value":"0.0","bestValue":false},{"metric":"files","value":"1"},{"metric":"duplicated_lines_density","value":"0.0","bestValue":true},{"metric":"test_success_density","value":"100.0","bestValue":true}]},{"id":"AYJVb5ukILU70yBXuTi-","key":"fga-eps-mds_2022.1-EuPescador-User:src/utils","name":"utils","qualifier":"DIR","path":"src/utils","measures":[{"metric":"duplicated_lines_density","value":"0.0","bestValue":true},{"metric":"functions","value":"1"},{"metric":"security_rating","value":"1.0","bestValue":true},{"metric":"files","value":"1"},{"metric":"complexity","value":"2"},{"metric":"ncloc","value":"9"},{"metric":"coverage","value":"0.0","bestValue":false},{"metric":"reliability_rating","value":"1.0","bestValue":true},{"metric":"comment_lines_density","value":"0.0","bestValue":false}]}]}